[
  {
    "RegistrationNumber": "SPUS46885",
    "CampaignName": "Minnesota 1 Summer 2024",
    "RegistrationStatus": "Undecided",
    "Contact_Zip": "55410",
    "Contact_state": "MN",
    "Product_RoofPitch": "Inclined",
    "Product_RoofOrientation": "SouthWest",
    "Product_KnowsAmountOfPanels": "0",
    "Product_AmountOfPanels": null,
    "Product_CanEstimateRoofSurface": "0",
    "Product_EstimatedRoofSizeFt": null,
    "Product_HomeSize": "Between2200And2800Ft",
    "Proposal_OptimalAmountOfPanels": 17,
    "Contact_LowMediumIncome": 0,
    "Contact_Utility": "Xcel",
    "Product_NumberOfStories": 2
  },
  {
    "RegistrationNumber": "SPUS54999",
    "CampaignName": "Minnesota 1 Summer 2024",
    "RegistrationStatus": "Undecided",
    "Contact_Zip": "55427",
    "Contact_state": "MN",
    "Product_RoofPitch": "Inclined",
    "Product_RoofOrientation": "West",
    "Product_KnowsAmountOfPanels": "0",
    "Product_AmountOfPanels": null,
    "Product_CanEstimateRoofSurface": "0",
    "Product_EstimatedRoofSizeFt": null,
    "Product_HomeSize": "LargerThan2800Ft",
    "Proposal_OptimalAmountOfPanels": 31,
    "Contact_LowMediumIncome": 0,
    "Contact_Utility": "Xcel",
    "Product_NumberOfStories": 2
  },
  {
    "RegistrationNumber": "SPUS55599",
    "CampaignName": "Minnesota 1 Summer 2024",
    "RegistrationStatus": "Undecided",
    "Contact_Zip": "55422",
    "Contact_state": "MN",
    "Product_RoofPitch": "Inclined",
    "Product_RoofOrientation": "South",
    "Product_KnowsAmountOfPanels": "0",
    "Product_AmountOfPanels": null,
    "Product_CanEstimateRoofSurface": "1",
    "Product_EstimatedRoofSizeFt": 1200,
    "Product_HomeSize": "Between1600And2200Ft",
    "Proposal_OptimalAmountOfPanels": 16,
    "Contact_LowMediumIncome": 0,
    "Contact_Utility": "Xcel",
    "Product_NumberOfStories": 2
  },
  {
    "RegistrationNumber": "SPUS55404",
    "CampaignName": "Minnesota 1 Summer 2024",
    "RegistrationStatus": "Undecided",
    "Contact_Zip": "55417",
    "Contact_state": "MN",
    "Product_RoofPitch": "Inclined",
    "Product_RoofOrientation": "South",
    "Product_KnowsAmountOfPanels": "1",
    "Product_AmountOfPanels": 10,
    "Product_CanEstimateRoofSurface": null,
    "Product_EstimatedRoofSizeFt": null,
    "Product_HomeSize": null,
    "Proposal_OptimalAmountOfPanels": 10,
    "Contact_LowMediumIncome": 0,
    "Contact_Utility": "Xcel",
    "Product_NumberOfStories": 2
  },
  {
    "RegistrationNumber": "SPUS45788",
    "CampaignName": "Minnesota 1 Summer 2024",
    "RegistrationStatus": "Cancelled",
    "Contact_Zip": "55432",
    "Contact_state": "MN",
    "Product_RoofPitch": "Inclined",
    "Product_RoofOrientation": "West",
    "Product_KnowsAmountOfPanels": "0",
    "Product_AmountOfPanels": null,
    "Product_CanEstimateRoofSurface": "0",
    "Product_EstimatedRoofSizeFt": null,
    "Product_HomeSize": "Between1600And2200Ft",
    "Proposal_OptimalAmountOfPanels": 21,
    "Contact_LowMediumIncome": 0,
    "Contact_Utility": "Xcel",
    "Product_NumberOfStories": 2
  },
  {
    "RegistrationNumber": "SPUS63955",
    "CampaignName": "Minnesota 1 Summer 2024",
    "RegistrationStatus": "Undecided",
    "Contact_Zip": "55410",
    "Contact_state": "MN",
    "Product_RoofPitch": "Inclined",
    "Product_RoofOrientation": "West",
    "Product_KnowsAmountOfPanels": "1",
    "Product_AmountOfPanels": 18,
    "Product_CanEstimateRoofSurface": null,
    "Product_EstimatedRoofSizeFt": null,
    "Product_HomeSize": null,
    "Proposal_OptimalAmountOfPanels": 9,
    "Contact_LowMediumIncome": 0,
    "Contact_Utility": "Xcel",
    "Product_NumberOfStories": 1
  },
  {
    "RegistrationNumber": "SPUS55127",
    "CampaignName": "Minnesota 1 Summer 2024",
    "RegistrationStatus": "Undecided",
    "Contact_Zip": "55447",
    "Contact_state": "MN",
    "Product_RoofPitch": "Inclined",
    "Product_RoofOrientation": "South",
    "Product_KnowsAmountOfPanels": "0",
    "Product_AmountOfPanels": null,
    "Product_CanEstimateRoofSurface": "0",
    "Product_EstimatedRoofSizeFt": null,
    "Product_HomeSize": "LargerThan2800Ft",
    "Proposal_OptimalAmountOfPanels": 25,
    "Contact_LowMediumIncome": 0,
    "Contact_Utility": "Xcel",
    "Product_NumberOfStories": 2
  },
  {
    "RegistrationNumber": "SPUS55456",
    "CampaignName": "Minnesota 1 Summer 2024",
    "RegistrationStatus": "Accepted",
    "Contact_Zip": "55407",
    "Contact_state": "MN",
    "Product_RoofPitch": "Inclined",
    "Product_RoofOrientation": "SouthWest",
    "Product_KnowsAmountOfPanels": "0",
    "Product_AmountOfPanels": null,
    "Product_CanEstimateRoofSurface": "0",
    "Product_EstimatedRoofSizeFt": null,
    "Product_HomeSize": "Between1000And1600Ft",
    "Proposal_OptimalAmountOfPanels": 11,
    "Contact_LowMediumIncome": 1,
    "Contact_Utility": "Xcel",
    "Product_NumberOfStories": 2
  },
  {
    "RegistrationNumber": "SPUS61381",
    "CampaignName": "Minnesota 1 Summer 2024",
    "RegistrationStatus": "Undecided",
    "Contact_Zip": "55419",
    "Contact_state": "MN",
    "Product_RoofPitch": "Inclined",
    "Product_RoofOrientation": "SouthWest",
    "Product_KnowsAmountOfPanels": "0",
    "Product_AmountOfPanels": null,
    "Product_CanEstimateRoofSurface": "0",
    "Product_EstimatedRoofSizeFt": null,
    "Product_HomeSize": "Between2200And2800Ft",
    "Proposal_OptimalAmountOfPanels": 27,
    "Contact_LowMediumIncome": 0,
    "Contact_Utility": "Xcel",
    "Product_NumberOfStories": 1
  },
  {
    "RegistrationNumber": "SPUS52157",
    "CampaignName": "Minnesota 1 Summer 2024",
    "RegistrationStatus": "Undecided",
    "Contact_Zip": "55409",
    "Contact_state": "MN",
    "Product_RoofPitch": "Sharp",
    "Product_RoofOrientation": "SouthWest",
    "Product_KnowsAmountOfPanels": "1",
    "Product_AmountOfPanels": 12,
    "Product_CanEstimateRoofSurface": null,
    "Product_EstimatedRoofSizeFt": null,
    "Product_HomeSize": "Between1000And1600Ft",
    "Proposal_OptimalAmountOfPanels": 12,
    "Contact_LowMediumIncome": 0,
    "Contact_Utility": "Xcel",
    "Product_NumberOfStories": 2
  },
  {
    "RegistrationNumber": "SPUS55640",
    "CampaignName": "Minnesota 1 Summer 2024",
    "RegistrationStatus": "Accepted",
    "Contact_Zip": "55419",
    "Contact_state": "MN",
    "Product_RoofPitch": "Inclined",
    "Product_RoofOrientation": "SouthWest",
    "Product_KnowsAmountOfPanels": "0",
    "Product_AmountOfPanels": null,
    "Product_CanEstimateRoofSurface": "0",
    "Product_EstimatedRoofSizeFt": null,
    "Product_HomeSize": "Between1600And2200Ft",
    "Proposal_OptimalAmountOfPanels": 10,
    "Contact_LowMediumIncome": 0,
    "Contact_Utility": "Xcel",
    "Product_NumberOfStories": 2
  },
  {
    "RegistrationNumber": "SPUS54945",
    "CampaignName": "Minnesota 1 Summer 2024",
    "RegistrationStatus": "Undecided",
    "Contact_Zip": "55405",
    "Contact_state": "MN",
    "Product_RoofPitch": "Inclined",
    "Product_RoofOrientation": "West",
    "Product_KnowsAmountOfPanels": "0",
    "Product_AmountOfPanels": null,
    "Product_CanEstimateRoofSurface": "1",
    "Product_EstimatedRoofSizeFt": 250,
    "Product_HomeSize": null,
    "Proposal_OptimalAmountOfPanels": 11,
    "Contact_LowMediumIncome": 0,
    "Contact_Utility": "Xcel",
    "Product_NumberOfStories": 1
  },
  {
    "RegistrationNumber": "SPUS47546",
    "CampaignName": "Minnesota 1 Summer 2024",
    "RegistrationStatus": "Undecided",
    "Contact_Zip": "55406",
    "Contact_state": "MN",
    "Product_RoofPitch": "Inclined",
    "Product_RoofOrientation": "South",
    "Product_KnowsAmountOfPanels": "0",
    "Product_AmountOfPanels": null,
    "Product_CanEstimateRoofSurface": "1",
    "Product_EstimatedRoofSizeFt": 450,
    "Product_HomeSize": null,
    "Proposal_OptimalAmountOfPanels": 11,
    "Contact_LowMediumIncome": 0,
    "Contact_Utility": "Xcel",
    "Product_NumberOfStories": 2
  },
  {
    "RegistrationNumber": "SPUS55691",
    "CampaignName": "Minnesota 1 Summer 2024",
    "RegistrationStatus": "Accepted",
    "Contact_Zip": "55419",
    "Contact_state": "MN",
    "Product_RoofPitch": "Inclined",
    "Product_RoofOrientation": "SouthWest",
    "Product_KnowsAmountOfPanels": "0",
    "Product_AmountOfPanels": null,
    "Product_CanEstimateRoofSurface": "0",
    "Product_EstimatedRoofSizeFt": null,
    "Product_HomeSize": "Between1600And2200Ft",
    "Proposal_OptimalAmountOfPanels": 20,
    "Contact_LowMediumIncome": 0,
    "Contact_Utility": "Xcel",
    "Product_NumberOfStories": 2
  },
  {
    "RegistrationNumber": "SPUS45813",
    "CampaignName": "Minnesota 1 Summer 2024",
    "RegistrationStatus": "Undecided",
    "Contact_Zip": "55409",
    "Contact_state": "MN",
    "Product_RoofPitch": "Sharp",
    "Product_RoofOrientation": "SouthWest",
    "Product_KnowsAmountOfPanels": "0",
    "Product_AmountOfPanels": null,
    "Product_CanEstimateRoofSurface": "0",
    "Product_EstimatedRoofSizeFt": null,
    "Product_HomeSize": "Between1000And1600Ft",
    "Proposal_OptimalAmountOfPanels": 22,
    "Contact_LowMediumIncome": 0,
    "Contact_Utility": "Xcel",
    "Product_NumberOfStories": 2
  },
  {
    "RegistrationNumber": "SPUS54753",
    "CampaignName": "Minnesota 1 Summer 2024",
    "RegistrationStatus": "Undecided",
    "Contact_Zip": "55424",
    "Contact_state": "MN",
    "Product_RoofPitch": "Inclined",
    "Product_RoofOrientation": "South",
    "Product_KnowsAmountOfPanels": "0",
    "Product_AmountOfPanels": null,
    "Product_CanEstimateRoofSurface": "0",
    "Product_EstimatedRoofSizeFt": null,
    "Product_HomeSize": "Between2200And2800Ft",
    "Proposal_OptimalAmountOfPanels": 17,
    "Contact_LowMediumIncome": 0,
    "Contact_Utility": "Xcel",
    "Product_NumberOfStories": 1
  },
  {
    "RegistrationNumber": "SPUS62734",
    "CampaignName": "Minnesota 1 Summer 2024",
    "RegistrationStatus": "Accepted",
    "Contact_Zip": "55423",
    "Contact_state": "MN",
    "Product_RoofPitch": "Inclined",
    "Product_RoofOrientation": "SouthWest",
    "Product_KnowsAmountOfPanels": "0",
    "Product_AmountOfPanels": null,
    "Product_CanEstimateRoofSurface": "1",
    "Product_EstimatedRoofSizeFt": 1500,
    "Product_HomeSize": null,
    "Proposal_OptimalAmountOfPanels": 8,
    "Contact_LowMediumIncome": 0,
    "Contact_Utility": "Xcel",
    "Product_NumberOfStories": 1
  },
  {
    "RegistrationNumber": "SPUS54992",
    "CampaignName": "Minnesota 1 Summer 2024",
    "RegistrationStatus": "Accepted",
    "Contact_Zip": "55412",
    "Contact_state": "MN",
    "Product_RoofPitch": "Inclined",
    "Product_RoofOrientation": "South",
    "Product_KnowsAmountOfPanels": "1",
    "Product_AmountOfPanels": 24,
    "Product_CanEstimateRoofSurface": null,
    "Product_EstimatedRoofSizeFt": null,
    "Product_HomeSize": null,
    "Proposal_OptimalAmountOfPanels": 18,
    "Contact_LowMediumIncome": 0,
    "Contact_Utility": "Xcel",
    "Product_NumberOfStories": 2
  },
  {
    "RegistrationNumber": "SPUS63873",
    "CampaignName": "Minnesota 1 Summer 2024",
    "RegistrationStatus": "Accepted",
    "Contact_Zip": "55406",
    "Contact_state": "MN",
    "Product_RoofPitch": "Inclined",
    "Product_RoofOrientation": "SouthWest",
    "Product_KnowsAmountOfPanels": "0",
    "Product_AmountOfPanels": null,
    "Product_CanEstimateRoofSurface": "0",
    "Product_EstimatedRoofSizeFt": null,
    "Product_HomeSize": "Between2200And2800Ft",
    "Proposal_OptimalAmountOfPanels": 33,
    "Contact_LowMediumIncome": 0,
    "Contact_Utility": "Xcel",
    "Product_NumberOfStories": 1
  },
  {
    "RegistrationNumber": "SPUS55784",
    "CampaignName": "Minnesota 1 Summer 2024",
    "RegistrationStatus": "Declined",
    "Contact_Zip": "55419",
    "Contact_state": "MN",
    "Product_RoofPitch": "Inclined",
    "Product_RoofOrientation": "South",
    "Product_KnowsAmountOfPanels": "0",
    "Product_AmountOfPanels": null,
    "Product_CanEstimateRoofSurface": "1",
    "Product_EstimatedRoofSizeFt": 3400,
    "Product_HomeSize": null,
    "Proposal_OptimalAmountOfPanels": 11,
    "Contact_LowMediumIncome": 0,
    "Contact_Utility": "Xcel",
    "Product_NumberOfStories": 2
  },
  {
    "RegistrationNumber": "SPUS61513",
    "CampaignName": "Minnesota 1 Summer 2024",
    "RegistrationStatus": "Undecided",
    "Contact_Zip": "55423",
    "Contact_state": "MN",
    "Product_RoofPitch": "Inclined",
    "Product_RoofOrientation": "South",
    "Product_KnowsAmountOfPanels": "0",
    "Product_AmountOfPanels": null,
    "Product_CanEstimateRoofSurface": "1",
    "Product_EstimatedRoofSizeFt": 1200,
    "Product_HomeSize": null,
    "Proposal_OptimalAmountOfPanels": 32,
    "Contact_LowMediumIncome": 0,
    "Contact_Utility": "Xcel",
    "Product_NumberOfStories": 2
  },
  {
    "RegistrationNumber": "SPUS55547",
    "CampaignName": "Minnesota 1 Summer 2024",
    "RegistrationStatus": "Undecided",
    "Contact_Zip": "55409",
    "Contact_state": "MN",
    "Product_RoofPitch": "Inclined",
    "Product_RoofOrientation": "South",
    "Product_KnowsAmountOfPanels": "0",
    "Product_AmountOfPanels": null,
    "Product_CanEstimateRoofSurface": "0",
    "Product_EstimatedRoofSizeFt": null,
    "Product_HomeSize": "Between1000And1600Ft",
    "Proposal_OptimalAmountOfPanels": 14,
    "Contact_LowMediumIncome": 0,
    "Contact_Utility": "Xcel",
    "Product_NumberOfStories": 2
  },
  {
    "RegistrationNumber": "SPUS61918",
    "CampaignName": "Minnesota 1 Summer 2024",
    "RegistrationStatus": "Accepted",
    "Contact_Zip": "55419",
    "Contact_state": "MN",
    "Product_RoofPitch": "Inclined",
    "Product_RoofOrientation": "West",
    "Product_KnowsAmountOfPanels": "0",
    "Product_AmountOfPanels": null,
    "Product_CanEstimateRoofSurface": "0",
    "Product_EstimatedRoofSizeFt": null,
    "Product_HomeSize": "Between1600And2200Ft",
    "Proposal_OptimalAmountOfPanels": 21,
    "Contact_LowMediumIncome": 0,
    "Contact_Utility": "Xcel",
    "Product_NumberOfStories": 1
  },
  {
    "RegistrationNumber": "SPUS62100",
    "CampaignName": "Minnesota 1 Summer 2024",
    "RegistrationStatus": "Undecided",
    "Contact_Zip": "55419",
    "Contact_state": "MN",
    "Product_RoofPitch": "Inclined",
    "Product_RoofOrientation": "West",
    "Product_KnowsAmountOfPanels": "0",
    "Product_AmountOfPanels": null,
    "Product_CanEstimateRoofSurface": "1",
    "Product_EstimatedRoofSizeFt": 399,
    "Product_HomeSize": "Between2200And2800Ft",
    "Proposal_OptimalAmountOfPanels": 19,
    "Contact_LowMediumIncome": 0,
    "Contact_Utility": "Xcel",
    "Product_NumberOfStories": 2
  },
  {
    "RegistrationNumber": "SPUS54964",
    "CampaignName": "Minnesota 1 Summer 2024",
    "RegistrationStatus": "Undecided",
    "Contact_Zip": "55424",
    "Contact_state": "MN",
    "Product_RoofPitch": "Inclined",
    "Product_RoofOrientation": "East",
    "Product_KnowsAmountOfPanels": "0",
    "Product_AmountOfPanels": null,
    "Product_CanEstimateRoofSurface": "0",
    "Product_EstimatedRoofSizeFt": null,
    "Product_HomeSize": "Between1600And2200Ft",
    "Proposal_OptimalAmountOfPanels": 26,
    "Contact_LowMediumIncome": 0,
    "Contact_Utility": "Xcel",
    "Product_NumberOfStories": 2
  },
  {
    "RegistrationNumber": "SPUS62778",
    "CampaignName": "Minnesota 1 Summer 2024",
    "RegistrationStatus": "Accepted",
    "Contact_Zip": "55406",
    "Contact_state": "MN",
    "Product_RoofPitch": "Inclined",
    "Product_RoofOrientation": "SouthWest",
    "Product_KnowsAmountOfPanels": "0",
    "Product_AmountOfPanels": null,
    "Product_CanEstimateRoofSurface": "0",
    "Product_EstimatedRoofSizeFt": null,
    "Product_HomeSize": "Between1000And1600Ft",
    "Proposal_OptimalAmountOfPanels": 10,
    "Contact_LowMediumIncome": 0,
    "Contact_Utility": "Xcel",
    "Product_NumberOfStories": 1
  },
  {
    "RegistrationNumber": "SPUS61551",
    "CampaignName": "Minnesota 1 Summer 2024",
    "RegistrationStatus": "Accepted",
    "Contact_Zip": "55418",
    "Contact_state": "MN",
    "Product_RoofPitch": "Inclined",
    "Product_RoofOrientation": "South",
    "Product_KnowsAmountOfPanels": "0",
    "Product_AmountOfPanels": null,
    "Product_CanEstimateRoofSurface": "1",
    "Product_EstimatedRoofSizeFt": 1030,
    "Product_HomeSize": "Between1000And1600Ft",
    "Proposal_OptimalAmountOfPanels": 14,
    "Contact_LowMediumIncome": 0,
    "Contact_Utility": "Xcel",
    "Product_NumberOfStories": 1
  },
  {
    "RegistrationNumber": "SPUS56365",
    "CampaignName": "Minnesota 1 Summer 2024",
    "RegistrationStatus": "Accepted",
    "Contact_Zip": "55422",
    "Contact_state": "MN",
    "Product_RoofPitch": "Inclined",
    "Product_RoofOrientation": "East",
    "Product_KnowsAmountOfPanels": "0",
    "Product_AmountOfPanels": null,
    "Product_CanEstimateRoofSurface": "0",
    "Product_EstimatedRoofSizeFt": null,
    "Product_HomeSize": "LargerThan2800Ft",
    "Proposal_OptimalAmountOfPanels": 19,
    "Contact_LowMediumIncome": 0,
    "Contact_Utility": "Xcel",
    "Product_NumberOfStories": 1
  },
  {
    "RegistrationNumber": "SPUS56006",
    "CampaignName": "Minnesota 1 Summer 2024",
    "RegistrationStatus": "Accepted",
    "Contact_Zip": "55416",
    "Contact_state": "MN",
    "Product_RoofPitch": "Flat",
    "Product_RoofOrientation": null,
    "Product_KnowsAmountOfPanels": "0",
    "Product_AmountOfPanels": null,
    "Product_CanEstimateRoofSurface": "0",
    "Product_EstimatedRoofSizeFt": null,
    "Product_HomeSize": "Between1600And2200Ft",
    "Proposal_OptimalAmountOfPanels": 20,
    "Contact_LowMediumIncome": 0,
    "Contact_Utility": "Xcel",
    "Product_NumberOfStories": 1
  },
  {
    "RegistrationNumber": "SPUS55557",
    "CampaignName": "Minnesota 1 Summer 2024",
    "RegistrationStatus": "Declined",
    "Contact_Zip": "55418",
    "Contact_state": "MN",
    "Product_RoofPitch": "Inclined",
    "Product_RoofOrientation": "South",
    "Product_KnowsAmountOfPanels": "0",
    "Product_AmountOfPanels": null,
    "Product_CanEstimateRoofSurface": "0",
    "Product_EstimatedRoofSizeFt": null,
    "Product_HomeSize": "SmallerThan1000Ft",
    "Proposal_OptimalAmountOfPanels": 8,
    "Contact_LowMediumIncome": 0,
    "Contact_Utility": "Xcel",
    "Product_NumberOfStories": 2
  },
  {
    "RegistrationNumber": "SPUS55519",
    "CampaignName": "Minnesota 1 Summer 2024",
    "RegistrationStatus": "Undecided",
    "Contact_Zip": "55426",
    "Contact_state": "MN",
    "Product_RoofPitch": "Inclined",
    "Product_RoofOrientation": "SouthWest",
    "Product_KnowsAmountOfPanels": "0",
    "Product_AmountOfPanels": null,
    "Product_CanEstimateRoofSurface": "0",
    "Product_EstimatedRoofSizeFt": null,
    "Product_HomeSize": "Between1600And2200Ft",
    "Proposal_OptimalAmountOfPanels": 23,
    "Contact_LowMediumIncome": 0,
    "Contact_Utility": "Xcel",
    "Product_NumberOfStories": 1
  },
  {
    "RegistrationNumber": "SPUS62731",
    "CampaignName": "Minnesota 1 Summer 2024",
    "RegistrationStatus": "Accepted",
    "Contact_Zip": "55410",
    "Contact_state": "MN",
    "Product_RoofPitch": "Sharp",
    "Product_RoofOrientation": "South",
    "Product_KnowsAmountOfPanels": "0",
    "Product_AmountOfPanels": null,
    "Product_CanEstimateRoofSurface": "0",
    "Product_EstimatedRoofSizeFt": null,
    "Product_HomeSize": "LargerThan2800Ft",
    "Proposal_OptimalAmountOfPanels": 47,
    "Contact_LowMediumIncome": 1,
    "Contact_Utility": "Xcel",
    "Product_NumberOfStories": 2
  },
  {
    "RegistrationNumber": "SPUS45840",
    "CampaignName": "Minnesota 1 Summer 2024",
    "RegistrationStatus": "Undecided",
    "Contact_Zip": "55410",
    "Contact_state": "MN",
    "Product_RoofPitch": "Inclined",
    "Product_RoofOrientation": "SouthWest",
    "Product_KnowsAmountOfPanels": "0",
    "Product_AmountOfPanels": null,
    "Product_CanEstimateRoofSurface": "0",
    "Product_EstimatedRoofSizeFt": null,
    "Product_HomeSize": "Between2200And2800Ft",
    "Proposal_OptimalAmountOfPanels": 26,
    "Contact_LowMediumIncome": 0,
    "Contact_Utility": "Xcel",
    "Product_NumberOfStories": 1
  },
  {
    "RegistrationNumber": "SPUS45785",
    "CampaignName": "Minnesota 1 Summer 2024",
    "RegistrationStatus": "Accepted",
    "Contact_Zip": "55403",
    "Contact_state": "MN",
    "Product_RoofPitch": "Sharp",
    "Product_RoofOrientation": "South",
    "Product_KnowsAmountOfPanels": "0",
    "Product_AmountOfPanels": null,
    "Product_CanEstimateRoofSurface": "1",
    "Product_EstimatedRoofSizeFt": 1200,
    "Product_HomeSize": null,
    "Proposal_OptimalAmountOfPanels": 33,
    "Contact_LowMediumIncome": 0,
    "Contact_Utility": "Xcel",
    "Product_NumberOfStories": 2
  },
  {
    "RegistrationNumber": "SPUS64056",
    "CampaignName": "Minnesota 1 Summer 2024",
    "RegistrationStatus": "Declined",
    "Contact_Zip": "55419",
    "Contact_state": "MN",
    "Product_RoofPitch": "Inclined",
    "Product_RoofOrientation": "SouthWest",
    "Product_KnowsAmountOfPanels": "0",
    "Product_AmountOfPanels": null,
    "Product_CanEstimateRoofSurface": "0",
    "Product_EstimatedRoofSizeFt": null,
    "Product_HomeSize": "Between1600And2200Ft",
    "Proposal_OptimalAmountOfPanels": 17,
    "Contact_LowMediumIncome": 0,
    "Contact_Utility": "Xcel",
    "Product_NumberOfStories": 1
  },
  {
    "RegistrationNumber": "SPUS62384",
    "CampaignName": "Minnesota 1 Summer 2024",
    "RegistrationStatus": "Accepted",
    "Contact_Zip": "55410",
    "Contact_state": "MN",
    "Product_RoofPitch": "Inclined",
    "Product_RoofOrientation": "SouthWest",
    "Product_KnowsAmountOfPanels": "0",
    "Product_AmountOfPanels": null,
    "Product_CanEstimateRoofSurface": "0",
    "Product_EstimatedRoofSizeFt": null,
    "Product_HomeSize": "Between1000And1600Ft",
    "Proposal_OptimalAmountOfPanels": 8,
    "Contact_LowMediumIncome": 0,
    "Contact_Utility": "Xcel",
    "Product_NumberOfStories": 2
  },
  {
    "RegistrationNumber": "SPUS61344",
    "CampaignName": "Minnesota 1 Summer 2024",
    "RegistrationStatus": "Accepted",
    "Contact_Zip": "55406",
    "Contact_state": "MN",
    "Product_RoofPitch": "Inclined",
    "Product_RoofOrientation": "West",
    "Product_KnowsAmountOfPanels": "0",
    "Product_AmountOfPanels": null,
    "Product_CanEstimateRoofSurface": "1",
    "Product_EstimatedRoofSizeFt": 576,
    "Product_HomeSize": "Between1600And2200Ft",
    "Proposal_OptimalAmountOfPanels": 21,
    "Contact_LowMediumIncome": 0,
    "Contact_Utility": "Xcel",
    "Product_NumberOfStories": 2
  },
  {
    "RegistrationNumber": "SPUS61819",
    "CampaignName": "Minnesota 1 Summer 2024",
    "RegistrationStatus": "Undecided",
    "Contact_Zip": "55446",
    "Contact_state": "MN",
    "Product_RoofPitch": "Sharp",
    "Product_RoofOrientation": "SouthWest",
    "Product_KnowsAmountOfPanels": "1",
    "Product_AmountOfPanels": 29,
    "Product_CanEstimateRoofSurface": null,
    "Product_EstimatedRoofSizeFt": null,
    "Product_HomeSize": null,
    "Proposal_OptimalAmountOfPanels": 18,
    "Contact_LowMediumIncome": 0,
    "Contact_Utility": "Xcel",
    "Product_NumberOfStories": 2
  },
  {
    "RegistrationNumber": "SPUS46542",
    "CampaignName": "Minnesota 1 Summer 2024",
    "RegistrationStatus": "Accepted",
    "Contact_Zip": "55403",
    "Contact_state": "MN",
    "Product_RoofPitch": "Flat",
    "Product_RoofOrientation": "SouthWest",
    "Product_KnowsAmountOfPanels": "0",
    "Product_AmountOfPanels": null,
    "Product_CanEstimateRoofSurface": "1",
    "Product_EstimatedRoofSizeFt": 3000,
    "Product_HomeSize": null,
    "Proposal_OptimalAmountOfPanels": 35,
    "Contact_LowMediumIncome": 0,
    "Contact_Utility": "Xcel",
    "Product_NumberOfStories": 3
  },
  {
    "RegistrationNumber": "SPUS54800",
    "CampaignName": "Minnesota 1 Summer 2024",
    "RegistrationStatus": "Accepted",
    "Contact_Zip": "55417",
    "Contact_state": "MN",
    "Product_RoofPitch": "Sharp",
    "Product_RoofOrientation": "SouthWest",
    "Product_KnowsAmountOfPanels": "0",
    "Product_AmountOfPanels": null,
    "Product_CanEstimateRoofSurface": "0",
    "Product_EstimatedRoofSizeFt": null,
    "Product_HomeSize": "Between1000And1600Ft",
    "Proposal_OptimalAmountOfPanels": 8,
    "Contact_LowMediumIncome": 0,
    "Contact_Utility": "Xcel",
    "Product_NumberOfStories": 2
  },
  {
    "RegistrationNumber": "SPUS61545",
    "CampaignName": "Minnesota 1 Summer 2024",
    "RegistrationStatus": "Accepted",
    "Contact_Zip": "55405",
    "Contact_state": "MN",
    "Product_RoofPitch": "Inclined",
    "Product_RoofOrientation": "West",
    "Product_KnowsAmountOfPanels": "0",
    "Product_AmountOfPanels": null,
    "Product_CanEstimateRoofSurface": "1",
    "Product_EstimatedRoofSizeFt": 520,
    "Product_HomeSize": "SmallerThan1000Ft",
    "Proposal_OptimalAmountOfPanels": 16,
    "Contact_LowMediumIncome": 0,
    "Contact_Utility": "Xcel",
    "Product_NumberOfStories": 1
  },
  {
    "RegistrationNumber": "SPUS64058",
    "CampaignName": "Minnesota 1 Summer 2024",
    "RegistrationStatus": "Accepted",
    "Contact_Zip": "55432",
    "Contact_state": "MN",
    "Product_RoofPitch": "Inclined",
    "Product_RoofOrientation": "SouthWest",
    "Product_KnowsAmountOfPanels": "0",
    "Product_AmountOfPanels": null,
    "Product_CanEstimateRoofSurface": "0",
    "Product_EstimatedRoofSizeFt": null,
    "Product_HomeSize": "Between1000And1600Ft",
    "Proposal_OptimalAmountOfPanels": 15,
    "Contact_LowMediumIncome": 0,
    "Contact_Utility": "Xcel",
    "Product_NumberOfStories": 1
  },
  {
    "RegistrationNumber": "SPUS55077",
    "CampaignName": "Minnesota 1 Summer 2024",
    "RegistrationStatus": "Accepted",
    "Contact_Zip": "55418",
    "Contact_state": "MN",
    "Product_RoofPitch": "Inclined",
    "Product_RoofOrientation": "South",
    "Product_KnowsAmountOfPanels": "1",
    "Product_AmountOfPanels": 14,
    "Product_CanEstimateRoofSurface": null,
    "Product_EstimatedRoofSizeFt": null,
    "Product_HomeSize": null,
    "Proposal_OptimalAmountOfPanels": 14,
    "Contact_LowMediumIncome": 0,
    "Contact_Utility": "Xcel",
    "Product_NumberOfStories": 2
  },
  {
    "RegistrationNumber": "SPUS45848",
    "CampaignName": "Minnesota 1 Summer 2024",
    "RegistrationStatus": "Undecided",
    "Contact_Zip": "55407",
    "Contact_state": "MN",
    "Product_RoofPitch": "Inclined",
    "Product_RoofOrientation": "East",
    "Product_KnowsAmountOfPanels": "0",
    "Product_AmountOfPanels": null,
    "Product_CanEstimateRoofSurface": "1",
    "Product_EstimatedRoofSizeFt": 430,
    "Product_HomeSize": null,
    "Proposal_OptimalAmountOfPanels": 11,
    "Contact_LowMediumIncome": 0,
    "Contact_Utility": "Xcel",
    "Product_NumberOfStories": 1
  },
  {
    "RegistrationNumber": "SPUS55931",
    "CampaignName": "Minnesota 1 Summer 2024",
    "RegistrationStatus": "Declined",
    "Contact_Zip": "55406",
    "Contact_state": "MN",
    "Product_RoofPitch": "Inclined",
    "Product_RoofOrientation": "SouthWest",
    "Product_KnowsAmountOfPanels": "0",
    "Product_AmountOfPanels": null,
    "Product_CanEstimateRoofSurface": "0",
    "Product_EstimatedRoofSizeFt": null,
    "Product_HomeSize": "Between1000And1600Ft",
    "Proposal_OptimalAmountOfPanels": 19,
    "Contact_LowMediumIncome": 0,
    "Contact_Utility": "Xcel",
    "Product_NumberOfStories": 2
  },
  {
    "RegistrationNumber": "SPUS54876",
    "CampaignName": "Minnesota 1 Summer 2024",
    "RegistrationStatus": "Accepted",
    "Contact_Zip": "55405",
    "Contact_state": "MN",
    "Product_RoofPitch": "Sharp",
    "Product_RoofOrientation": "SouthEast",
    "Product_KnowsAmountOfPanels": "0",
    "Product_AmountOfPanels": null,
    "Product_CanEstimateRoofSurface": "0",
    "Product_EstimatedRoofSizeFt": null,
    "Product_HomeSize": "Between1600And2200Ft",
    "Proposal_OptimalAmountOfPanels": 19,
    "Contact_LowMediumIncome": 0,
    "Contact_Utility": "Xcel",
    "Product_NumberOfStories": 3
  },
  {
    "RegistrationNumber": "SPUS63917",
    "CampaignName": "Minnesota 1 Summer 2024",
    "RegistrationStatus": "Accepted",
    "Contact_Zip": "55414",
    "Contact_state": "MN",
    "Product_RoofPitch": "Sharp",
    "Product_RoofOrientation": "SouthWest",
    "Product_KnowsAmountOfPanels": "0",
    "Product_AmountOfPanels": null,
    "Product_CanEstimateRoofSurface": "0",
    "Product_EstimatedRoofSizeFt": null,
    "Product_HomeSize": "Between1000And1600Ft",
    "Proposal_OptimalAmountOfPanels": 20,
    "Contact_LowMediumIncome": 1,
    "Contact_Utility": "Xcel",
    "Product_NumberOfStories": 2
  },
  {
    "RegistrationNumber": "SPUS54854",
    "CampaignName": "Minnesota 1 Summer 2024",
    "RegistrationStatus": "Undecided",
    "Contact_Zip": "55427",
    "Contact_state": "MN",
    "Product_RoofPitch": "Inclined",
    "Product_RoofOrientation": "SouthWest",
    "Product_KnowsAmountOfPanels": "0",
    "Product_AmountOfPanels": null,
    "Product_CanEstimateRoofSurface": "0",
    "Product_EstimatedRoofSizeFt": null,
    "Product_HomeSize": "Between1600And2200Ft",
    "Proposal_OptimalAmountOfPanels": 17,
    "Contact_LowMediumIncome": 0,
    "Contact_Utility": "Xcel",
    "Product_NumberOfStories": 2
  },
  {
    "RegistrationNumber": "SPUS63349",
    "CampaignName": "Minnesota 1 Summer 2024",
    "RegistrationStatus": "Undecided",
    "Contact_Zip": "55418",
    "Contact_state": "MN",
    "Product_RoofPitch": "Sharp",
    "Product_RoofOrientation": "South",
    "Product_KnowsAmountOfPanels": "1",
    "Product_AmountOfPanels": 8,
    "Product_CanEstimateRoofSurface": null,
    "Product_EstimatedRoofSizeFt": null,
    "Product_HomeSize": "Between1000And1600Ft",
    "Proposal_OptimalAmountOfPanels": 8,
    "Contact_LowMediumIncome": 1,
    "Contact_Utility": "Xcel",
    "Product_NumberOfStories": 2
  },
  {
    "RegistrationNumber": "SPUS55187",
    "CampaignName": "Minnesota 1 Summer 2024",
    "RegistrationStatus": "Undecided",
    "Contact_Zip": "55412",
    "Contact_state": "MN",
    "Product_RoofPitch": "Inclined",
    "Product_RoofOrientation": "SouthWest",
    "Product_KnowsAmountOfPanels": "0",
    "Product_AmountOfPanels": null,
    "Product_CanEstimateRoofSurface": "0",
    "Product_EstimatedRoofSizeFt": null,
    "Product_HomeSize": "Between1600And2200Ft",
    "Proposal_OptimalAmountOfPanels": 17,
    "Contact_LowMediumIncome": 0,
    "Contact_Utility": "Xcel",
    "Product_NumberOfStories": 2
  },
  {
    "RegistrationNumber": "SPUS46475",
    "CampaignName": "Minnesota 1 Summer 2024",
    "RegistrationStatus": "Undecided",
    "Contact_Zip": "55406",
    "Contact_state": "MN",
    "Product_RoofPitch": "Inclined",
    "Product_RoofOrientation": "SouthWest",
    "Product_KnowsAmountOfPanels": "0",
    "Product_AmountOfPanels": null,
    "Product_CanEstimateRoofSurface": "1",
    "Product_EstimatedRoofSizeFt": 850,
    "Product_HomeSize": "SmallerThan1000Ft",
    "Proposal_OptimalAmountOfPanels": 16,
    "Contact_LowMediumIncome": 0,
    "Contact_Utility": "Xcel",
    "Product_NumberOfStories": 1
  },
  {
    "RegistrationNumber": "SPUS63895",
    "CampaignName": "Minnesota 1 Summer 2024",
    "RegistrationStatus": "Accepted",
    "Contact_Zip": "55418",
    "Contact_state": "MN",
    "Product_RoofPitch": "Inclined",
    "Product_RoofOrientation": "SouthWest",
    "Product_KnowsAmountOfPanels": "0",
    "Product_AmountOfPanels": null,
    "Product_CanEstimateRoofSurface": "0",
    "Product_EstimatedRoofSizeFt": null,
    "Product_HomeSize": "SmallerThan1000Ft",
    "Proposal_OptimalAmountOfPanels": 21,
    "Contact_LowMediumIncome": 0,
    "Contact_Utility": "Xcel",
    "Product_NumberOfStories": 1
  },
  {
    "RegistrationNumber": "SPUS56252",
    "CampaignName": "Minnesota 1 Summer 2024",
    "RegistrationStatus": "Accepted",
    "Contact_Zip": "55419",
    "Contact_state": "MN",
    "Product_RoofPitch": "Inclined",
    "Product_RoofOrientation": "West",
    "Product_KnowsAmountOfPanels": "0",
    "Product_AmountOfPanels": null,
    "Product_CanEstimateRoofSurface": "1",
    "Product_EstimatedRoofSizeFt": 1200,
    "Product_HomeSize": null,
    "Proposal_OptimalAmountOfPanels": 10,
    "Contact_LowMediumIncome": 0,
    "Contact_Utility": "Xcel",
    "Product_NumberOfStories": 2
  },
  {
    "RegistrationNumber": "SPUS63653",
    "CampaignName": "Minnesota 1 Summer 2024",
    "RegistrationStatus": "Undecided",
    "Contact_Zip": "55423",
    "Contact_state": "MN",
    "Product_RoofPitch": "Inclined",
    "Product_RoofOrientation": "SouthWest",
    "Product_KnowsAmountOfPanels": "0",
    "Product_AmountOfPanels": null,
    "Product_CanEstimateRoofSurface": "1",
    "Product_EstimatedRoofSizeFt": 1600,
    "Product_HomeSize": "Between1600And2200Ft",
    "Proposal_OptimalAmountOfPanels": 26,
    "Contact_LowMediumIncome": 0,
    "Contact_Utility": "Xcel",
    "Product_NumberOfStories": 2
  },
  {
    "RegistrationNumber": "SPUS46281",
    "CampaignName": "Minnesota 1 Summer 2024",
    "RegistrationStatus": "Undecided",
    "Contact_Zip": "55419",
    "Contact_state": "MN",
    "Product_RoofPitch": "Inclined",
    "Product_RoofOrientation": "SouthWest",
    "Product_KnowsAmountOfPanels": "0",
    "Product_AmountOfPanels": null,
    "Product_CanEstimateRoofSurface": "0",
    "Product_EstimatedRoofSizeFt": null,
    "Product_HomeSize": "Between2200And2800Ft",
    "Proposal_OptimalAmountOfPanels": 31,
    "Contact_LowMediumIncome": 0,
    "Contact_Utility": "Xcel",
    "Product_NumberOfStories": 2
  },
  {
    "RegistrationNumber": "SPUS46210",
    "CampaignName": "Minnesota 1 Summer 2024",
    "RegistrationStatus": "Declined",
    "Contact_Zip": "55419",
    "Contact_state": "MN",
    "Product_RoofPitch": "Inclined",
    "Product_RoofOrientation": "SouthWest",
    "Product_KnowsAmountOfPanels": "0",
    "Product_AmountOfPanels": null,
    "Product_CanEstimateRoofSurface": "0",
    "Product_EstimatedRoofSizeFt": null,
    "Product_HomeSize": "Between2200And2800Ft",
    "Proposal_OptimalAmountOfPanels": 27,
    "Contact_LowMediumIncome": 0,
    "Contact_Utility": "Xcel",
    "Product_NumberOfStories": 1
  },
  {
    "RegistrationNumber": "SPUS55832",
    "CampaignName": "Minnesota 1 Summer 2024",
    "RegistrationStatus": "Declined",
    "Contact_Zip": "55419",
    "Contact_state": "MN",
    "Product_RoofPitch": "Inclined",
    "Product_RoofOrientation": "West",
    "Product_KnowsAmountOfPanels": "0",
    "Product_AmountOfPanels": null,
    "Product_CanEstimateRoofSurface": "1",
    "Product_EstimatedRoofSizeFt": 1400,
    "Product_HomeSize": "Between1600And2200Ft",
    "Proposal_OptimalAmountOfPanels": 25,
    "Contact_LowMediumIncome": 0,
    "Contact_Utility": "Xcel",
    "Product_NumberOfStories": 1
  },
  {
    "RegistrationNumber": "SPUS55195",
    "CampaignName": "Minnesota 1 Summer 2024",
    "RegistrationStatus": "Undecided",
    "Contact_Zip": "55407",
    "Contact_state": "MN",
    "Product_RoofPitch": "Inclined",
    "Product_RoofOrientation": "SouthWest",
    "Product_KnowsAmountOfPanels": "0",
    "Product_AmountOfPanels": null,
    "Product_CanEstimateRoofSurface": "0",
    "Product_EstimatedRoofSizeFt": null,
    "Product_HomeSize": "Between2200And2800Ft",
    "Proposal_OptimalAmountOfPanels": 12,
    "Contact_LowMediumIncome": 0,
    "Contact_Utility": "Xcel",
    "Product_NumberOfStories": 2
  },
  {
    "RegistrationNumber": "SPUS61746",
    "CampaignName": "Minnesota 1 Summer 2024",
    "RegistrationStatus": "Accepted",
    "Contact_Zip": "55406",
    "Contact_state": "MN",
    "Product_RoofPitch": "Inclined",
    "Product_RoofOrientation": "South",
    "Product_KnowsAmountOfPanels": "0",
    "Product_AmountOfPanels": null,
    "Product_CanEstimateRoofSurface": "0",
    "Product_EstimatedRoofSizeFt": null,
    "Product_HomeSize": "Between1600And2200Ft",
    "Proposal_OptimalAmountOfPanels": 8,
    "Contact_LowMediumIncome": 0,
    "Contact_Utility": "Xcel",
    "Product_NumberOfStories": 2
  },
  {
    "RegistrationNumber": "SPUS47094",
    "CampaignName": "Minnesota 1 Summer 2024",
    "RegistrationStatus": "Accepted",
    "Contact_Zip": "55404",
    "Contact_state": "MN",
    "Product_RoofPitch": "Inclined",
    "Product_RoofOrientation": "SouthWest",
    "Product_KnowsAmountOfPanels": "0",
    "Product_AmountOfPanels": null,
    "Product_CanEstimateRoofSurface": "0",
    "Product_EstimatedRoofSizeFt": null,
    "Product_HomeSize": "LargerThan2800Ft",
    "Proposal_OptimalAmountOfPanels": 44,
    "Contact_LowMediumIncome": 0,
    "Contact_Utility": "Xcel",
    "Product_NumberOfStories": 2
  },
  {
    "RegistrationNumber": "SPUS54598",
    "CampaignName": "Minnesota 1 Summer 2024",
    "RegistrationStatus": "Undecided",
    "Contact_Zip": "55421",
    "Contact_state": "MN",
    "Product_RoofPitch": "Sharp",
    "Product_RoofOrientation": "East",
    "Product_KnowsAmountOfPanels": "0",
    "Product_AmountOfPanels": null,
    "Product_CanEstimateRoofSurface": "0",
    "Product_EstimatedRoofSizeFt": null,
    "Product_HomeSize": "Between2200And2800Ft",
    "Proposal_OptimalAmountOfPanels": 34,
    "Contact_LowMediumIncome": 1,
    "Contact_Utility": "Xcel",
    "Product_NumberOfStories": 2
  },
  {
    "RegistrationNumber": "SPUS61481",
    "CampaignName": "Minnesota 1 Summer 2024",
    "RegistrationStatus": "Undecided",
    "Contact_Zip": "55410",
    "Contact_state": "MN",
    "Product_RoofPitch": "Inclined",
    "Product_RoofOrientation": "East",
    "Product_KnowsAmountOfPanels": "1",
    "Product_AmountOfPanels": 12,
    "Product_CanEstimateRoofSurface": null,
    "Product_EstimatedRoofSizeFt": null,
    "Product_HomeSize": "Between1000And1600Ft",
    "Proposal_OptimalAmountOfPanels": 12,
    "Contact_LowMediumIncome": 0,
    "Contact_Utility": "Xcel",
    "Product_NumberOfStories": 1
  },
  {
    "RegistrationNumber": "SPUS55418",
    "CampaignName": "Minnesota 1 Summer 2024",
    "RegistrationStatus": "Undecided",
    "Contact_Zip": "55406",
    "Contact_state": "MN",
    "Product_RoofPitch": "Inclined",
    "Product_RoofOrientation": "SouthWest",
    "Product_KnowsAmountOfPanels": "0",
    "Product_AmountOfPanels": null,
    "Product_CanEstimateRoofSurface": "0",
    "Product_EstimatedRoofSizeFt": null,
    "Product_HomeSize": "Between1600And2200Ft",
    "Proposal_OptimalAmountOfPanels": 17,
    "Contact_LowMediumIncome": 0,
    "Contact_Utility": "Xcel",
    "Product_NumberOfStories": 2
  },
  {
    "RegistrationNumber": "SPUS56232",
    "CampaignName": "Minnesota 1 Summer 2024",
    "RegistrationStatus": "Accepted",
    "Contact_Zip": "55406",
    "Contact_state": "MN",
    "Product_RoofPitch": "Inclined",
    "Product_RoofOrientation": "South",
    "Product_KnowsAmountOfPanels": "0",
    "Product_AmountOfPanels": null,
    "Product_CanEstimateRoofSurface": "1",
    "Product_EstimatedRoofSizeFt": 600,
    "Product_HomeSize": "Between1000And1600Ft",
    "Proposal_OptimalAmountOfPanels": 14,
    "Contact_LowMediumIncome": 0,
    "Contact_Utility": "Xcel",
    "Product_NumberOfStories": 2
  },
  {
    "RegistrationNumber": "SPUS61378",
    "CampaignName": "Minnesota 1 Summer 2024",
    "RegistrationStatus": "Undecided",
    "Contact_Zip": "55417",
    "Contact_state": "MN",
    "Product_RoofPitch": "Sharp",
    "Product_RoofOrientation": "South",
    "Product_KnowsAmountOfPanels": "0",
    "Product_AmountOfPanels": null,
    "Product_CanEstimateRoofSurface": "1",
    "Product_EstimatedRoofSizeFt": 770,
    "Product_HomeSize": null,
    "Proposal_OptimalAmountOfPanels": 18,
    "Contact_LowMediumIncome": 0,
    "Contact_Utility": "Xcel",
    "Product_NumberOfStories": 2
  },
  {
    "RegistrationNumber": "SPUS61851",
    "CampaignName": "Minnesota 1 Summer 2024",
    "RegistrationStatus": "Accepted",
    "Contact_Zip": "55418",
    "Contact_state": "MN",
    "Product_RoofPitch": "Inclined",
    "Product_RoofOrientation": "South",
    "Product_KnowsAmountOfPanels": "0",
    "Product_AmountOfPanels": null,
    "Product_CanEstimateRoofSurface": "0",
    "Product_EstimatedRoofSizeFt": null,
    "Product_HomeSize": "SmallerThan1000Ft",
    "Proposal_OptimalAmountOfPanels": 9,
    "Contact_LowMediumIncome": 0,
    "Contact_Utility": "Xcel",
    "Product_NumberOfStories": 1
  },
  {
    "RegistrationNumber": "SPUS54900",
    "CampaignName": "Minnesota 1 Summer 2024",
    "RegistrationStatus": "Undecided",
    "Contact_Zip": "55418",
    "Contact_state": "MN",
    "Product_RoofPitch": "Inclined",
    "Product_RoofOrientation": "South",
    "Product_KnowsAmountOfPanels": "0",
    "Product_AmountOfPanels": null,
    "Product_CanEstimateRoofSurface": "1",
    "Product_EstimatedRoofSizeFt": 1200,
    "Product_HomeSize": "Between1000And1600Ft",
    "Proposal_OptimalAmountOfPanels": 14,
    "Contact_LowMediumIncome": 0,
    "Contact_Utility": "Xcel",
    "Product_NumberOfStories": 2
  },
  {
    "RegistrationNumber": "SPUS55305",
    "CampaignName": "Minnesota 1 Summer 2024",
    "RegistrationStatus": "Accepted",
    "Contact_Zip": "55405",
    "Contact_state": "MN",
    "Product_RoofPitch": "Inclined",
    "Product_RoofOrientation": "South",
    "Product_KnowsAmountOfPanels": "0",
    "Product_AmountOfPanels": null,
    "Product_CanEstimateRoofSurface": "1",
    "Product_EstimatedRoofSizeFt": 500,
    "Product_HomeSize": null,
    "Proposal_OptimalAmountOfPanels": 8,
    "Contact_LowMediumIncome": 0,
    "Contact_Utility": "Xcel",
    "Product_NumberOfStories": 1
  },
  {
    "RegistrationNumber": "SPUS54933",
    "CampaignName": "Minnesota 1 Summer 2024",
    "RegistrationStatus": "Undecided",
    "Contact_Zip": "55409",
    "Contact_state": "MN",
    "Product_RoofPitch": "Inclined",
    "Product_RoofOrientation": "South",
    "Product_KnowsAmountOfPanels": "0",
    "Product_AmountOfPanels": null,
    "Product_CanEstimateRoofSurface": "0",
    "Product_EstimatedRoofSizeFt": null,
    "Product_HomeSize": "Between1600And2200Ft",
    "Proposal_OptimalAmountOfPanels": 8,
    "Contact_LowMediumIncome": 0,
    "Contact_Utility": "Xcel",
    "Product_NumberOfStories": 2
  },
  {
    "RegistrationNumber": "SPUS55405",
    "CampaignName": "Minnesota 1 Summer 2024",
    "RegistrationStatus": "Accepted",
    "Contact_Zip": "55406",
    "Contact_state": "MN",
    "Product_RoofPitch": "Inclined",
    "Product_RoofOrientation": "South",
    "Product_KnowsAmountOfPanels": "0",
    "Product_AmountOfPanels": null,
    "Product_CanEstimateRoofSurface": "1",
    "Product_EstimatedRoofSizeFt": 1346,
    "Product_HomeSize": null,
    "Proposal_OptimalAmountOfPanels": 12,
    "Contact_LowMediumIncome": 0,
    "Contact_Utility": "Xcel",
    "Product_NumberOfStories": 2
  },
  {
    "RegistrationNumber": "SPUS54872",
    "CampaignName": "Minnesota 1 Summer 2024",
    "RegistrationStatus": "Cancelled",
    "Contact_Zip": "55405",
    "Contact_state": "MN",
    "Product_RoofPitch": "Inclined",
    "Product_RoofOrientation": "East",
    "Product_KnowsAmountOfPanels": "0",
    "Product_AmountOfPanels": null,
    "Product_CanEstimateRoofSurface": "1",
    "Product_EstimatedRoofSizeFt": 3900,
    "Product_HomeSize": null,
    "Proposal_OptimalAmountOfPanels": null,
    "Contact_LowMediumIncome": 0,
    "Contact_Utility": "Xcel",
    "Product_NumberOfStories": 1
  },
  {
    "RegistrationNumber": "SPUS64005",
    "CampaignName": "Minnesota 1 Summer 2024",
    "RegistrationStatus": "Accepted",
    "Contact_Zip": "55406",
    "Contact_state": "MN",
    "Product_RoofPitch": "Inclined",
    "Product_RoofOrientation": "SouthWest",
    "Product_KnowsAmountOfPanels": "0",
    "Product_AmountOfPanels": null,
    "Product_CanEstimateRoofSurface": "1",
    "Product_EstimatedRoofSizeFt": 1150,
    "Product_HomeSize": null,
    "Proposal_OptimalAmountOfPanels": 8,
    "Contact_LowMediumIncome": 0,
    "Contact_Utility": "Xcel",
    "Product_NumberOfStories": 1
  },
  {
    "RegistrationNumber": "SPUS54199",
    "CampaignName": "Minnesota 1 Summer 2024",
    "RegistrationStatus": "Accepted",
    "Contact_Zip": "55104",
    "Contact_state": "MN",
    "Product_RoofPitch": "Inclined",
    "Product_RoofOrientation": "West",
    "Product_KnowsAmountOfPanels": "0",
    "Product_AmountOfPanels": null,
    "Product_CanEstimateRoofSurface": "1",
    "Product_EstimatedRoofSizeFt": 400,
    "Product_HomeSize": null,
    "Proposal_OptimalAmountOfPanels": 8,
    "Contact_LowMediumIncome": 0,
    "Contact_Utility": "Xcel",
    "Product_NumberOfStories": 1
  },
  {
    "RegistrationNumber": "SPUS47107",
    "CampaignName": "Minnesota 1 Summer 2024",
    "RegistrationStatus": "Accepted",
    "Contact_Zip": "55423",
    "Contact_state": "MN",
    "Product_RoofPitch": "Inclined",
    "Product_RoofOrientation": "SouthWest",
    "Product_KnowsAmountOfPanels": "0",
    "Product_AmountOfPanels": null,
    "Product_CanEstimateRoofSurface": "0",
    "Product_EstimatedRoofSizeFt": null,
    "Product_HomeSize": "Between1600And2200Ft",
    "Proposal_OptimalAmountOfPanels": 21,
    "Contact_LowMediumIncome": 0,
    "Contact_Utility": "Xcel",
    "Product_NumberOfStories": 1
  },
  {
    "RegistrationNumber": "SPUS46545",
    "CampaignName": "Minnesota 1 Summer 2024",
    "RegistrationStatus": "Undecided",
    "Contact_Zip": "55422",
    "Contact_state": "MN",
    "Product_RoofPitch": "Inclined",
    "Product_RoofOrientation": "SouthWest",
    "Product_KnowsAmountOfPanels": "0",
    "Product_AmountOfPanels": null,
    "Product_CanEstimateRoofSurface": "0",
    "Product_EstimatedRoofSizeFt": null,
    "Product_HomeSize": "Between1600And2200Ft",
    "Proposal_OptimalAmountOfPanels": 12,
    "Contact_LowMediumIncome": 1,
    "Contact_Utility": "Xcel",
    "Product_NumberOfStories": 1
  },
  {
    "RegistrationNumber": "SPUS55372",
    "CampaignName": "Minnesota 1 Summer 2024",
    "RegistrationStatus": "Declined",
    "Contact_Zip": "55442",
    "Contact_state": "MN",
    "Product_RoofPitch": "Sharp",
    "Product_RoofOrientation": "South",
    "Product_KnowsAmountOfPanels": "0",
    "Product_AmountOfPanels": null,
    "Product_CanEstimateRoofSurface": "0",
    "Product_EstimatedRoofSizeFt": null,
    "Product_HomeSize": "Between1600And2200Ft",
    "Proposal_OptimalAmountOfPanels": 12,
    "Contact_LowMediumIncome": 0,
    "Contact_Utility": "Xcel",
    "Product_NumberOfStories": 2
  },
  {
    "RegistrationNumber": "SPUS47350",
    "CampaignName": "Minnesota 1 Summer 2024",
    "RegistrationStatus": "Undecided",
    "Contact_Zip": "55404",
    "Contact_state": "MN",
    "Product_RoofPitch": "Sharp",
    "Product_RoofOrientation": "SouthWest",
    "Product_KnowsAmountOfPanels": "0",
    "Product_AmountOfPanels": null,
    "Product_CanEstimateRoofSurface": "0",
    "Product_EstimatedRoofSizeFt": null,
    "Product_HomeSize": "Between1600And2200Ft",
    "Proposal_OptimalAmountOfPanels": 17,
    "Contact_LowMediumIncome": 0,
    "Contact_Utility": "Xcel",
    "Product_NumberOfStories": 2
  },
  {
    "RegistrationNumber": "SPUS61707",
    "CampaignName": "Minnesota 1 Summer 2024",
    "RegistrationStatus": "Declined",
    "Contact_Zip": "55419",
    "Contact_state": "MN",
    "Product_RoofPitch": "Inclined",
    "Product_RoofOrientation": "SouthWest",
    "Product_KnowsAmountOfPanels": "0",
    "Product_AmountOfPanels": null,
    "Product_CanEstimateRoofSurface": "1",
    "Product_EstimatedRoofSizeFt": 368,
    "Product_HomeSize": "Between1600And2200Ft",
    "Proposal_OptimalAmountOfPanels": 20,
    "Contact_LowMediumIncome": 0,
    "Contact_Utility": "Xcel",
    "Product_NumberOfStories": 2
  },
  {
    "RegistrationNumber": "SPUS64042",
    "CampaignName": "Minnesota 1 Summer 2024",
    "RegistrationStatus": "Declined",
    "Contact_Zip": "55105",
    "Contact_state": "MN",
    "Product_RoofPitch": "Inclined",
    "Product_RoofOrientation": "East",
    "Product_KnowsAmountOfPanels": "0",
    "Product_AmountOfPanels": null,
    "Product_CanEstimateRoofSurface": "1",
    "Product_EstimatedRoofSizeFt": 528,
    "Product_HomeSize": null,
    "Proposal_OptimalAmountOfPanels": 20,
    "Contact_LowMediumIncome": 0,
    "Contact_Utility": "Xcel",
    "Product_NumberOfStories": 1
  },
  {
    "RegistrationNumber": "SPUS55079",
    "CampaignName": "Minnesota 1 Summer 2024",
    "RegistrationStatus": "Undecided",
    "Contact_Zip": "55405",
    "Contact_state": "MN",
    "Product_RoofPitch": "Flat",
    "Product_RoofOrientation": null,
    "Product_KnowsAmountOfPanels": "0",
    "Product_AmountOfPanels": null,
    "Product_CanEstimateRoofSurface": "1",
    "Product_EstimatedRoofSizeFt": 640,
    "Product_HomeSize": "Between2200And2800Ft",
    "Proposal_OptimalAmountOfPanels": 18,
    "Contact_LowMediumIncome": 0,
    "Contact_Utility": "Xcel",
    "Product_NumberOfStories": 2
  },
  {
    "RegistrationNumber": "SPUS55873",
    "CampaignName": "Minnesota 1 Summer 2024",
    "RegistrationStatus": "Accepted",
    "Contact_Zip": "55413",
    "Contact_state": "MN",
    "Product_RoofPitch": "Inclined",
    "Product_RoofOrientation": "SouthWest",
    "Product_KnowsAmountOfPanels": "0",
    "Product_AmountOfPanels": null,
    "Product_CanEstimateRoofSurface": "0",
    "Product_EstimatedRoofSizeFt": null,
    "Product_HomeSize": "Between2200And2800Ft",
    "Proposal_OptimalAmountOfPanels": 28,
    "Contact_LowMediumIncome": 1,
    "Contact_Utility": "Xcel",
    "Product_NumberOfStories": 2
  },
  {
    "RegistrationNumber": "SPUS61949",
    "CampaignName": "Minnesota 1 Summer 2024",
    "RegistrationStatus": "Undecided",
    "Contact_Zip": "55417",
    "Contact_state": "MN",
    "Product_RoofPitch": "Inclined",
    "Product_RoofOrientation": "West",
    "Product_KnowsAmountOfPanels": "0",
    "Product_AmountOfPanels": null,
    "Product_CanEstimateRoofSurface": "0",
    "Product_EstimatedRoofSizeFt": null,
    "Product_HomeSize": "Between1000And1600Ft",
    "Proposal_OptimalAmountOfPanels": 12,
    "Contact_LowMediumIncome": 0,
    "Contact_Utility": "Xcel",
    "Product_NumberOfStories": 2
  },
  {
    "RegistrationNumber": "SPUS46828",
    "CampaignName": "Minnesota 1 Summer 2024",
    "RegistrationStatus": "Undecided",
    "Contact_Zip": "55419",
    "Contact_state": "MN",
    "Product_RoofPitch": "Inclined",
    "Product_RoofOrientation": "South",
    "Product_KnowsAmountOfPanels": "0",
    "Product_AmountOfPanels": null,
    "Product_CanEstimateRoofSurface": "0",
    "Product_EstimatedRoofSizeFt": null,
    "Product_HomeSize": "Between1000And1600Ft",
    "Proposal_OptimalAmountOfPanels": 8,
    "Contact_LowMediumIncome": 0,
    "Contact_Utility": "Xcel",
    "Product_NumberOfStories": 2
  },
  {
    "RegistrationNumber": "SPUS45930",
    "CampaignName": "Minnesota 1 Summer 2024",
    "RegistrationStatus": "Undecided",
    "Contact_Zip": "55408",
    "Contact_state": "MN",
    "Product_RoofPitch": "Inclined",
    "Product_RoofOrientation": "SouthWest",
    "Product_KnowsAmountOfPanels": "0",
    "Product_AmountOfPanels": null,
    "Product_CanEstimateRoofSurface": "0",
    "Product_EstimatedRoofSizeFt": null,
    "Product_HomeSize": "Between1600And2200Ft",
    "Proposal_OptimalAmountOfPanels": 13,
    "Contact_LowMediumIncome": 0,
    "Contact_Utility": "Xcel",
    "Product_NumberOfStories": 2
  },
  {
    "RegistrationNumber": "SPUS63460",
    "CampaignName": "Minnesota 1 Summer 2024",
    "RegistrationStatus": "Undecided",
    "Contact_Zip": "55406",
    "Contact_state": "MN",
    "Product_RoofPitch": "Sharp",
    "Product_RoofOrientation": "South",
    "Product_KnowsAmountOfPanels": "0",
    "Product_AmountOfPanels": null,
    "Product_CanEstimateRoofSurface": "0",
    "Product_EstimatedRoofSizeFt": null,
    "Product_HomeSize": "Between1000And1600Ft",
    "Proposal_OptimalAmountOfPanels": 8,
    "Contact_LowMediumIncome": 0,
    "Contact_Utility": "Xcel",
    "Product_NumberOfStories": 2
  },
  {
    "RegistrationNumber": "SPUS46399",
    "CampaignName": "Minnesota 1 Summer 2024",
    "RegistrationStatus": "Undecided",
    "Contact_Zip": "55417",
    "Contact_state": "MN",
    "Product_RoofPitch": "Inclined",
    "Product_RoofOrientation": "East",
    "Product_KnowsAmountOfPanels": "0",
    "Product_AmountOfPanels": null,
    "Product_CanEstimateRoofSurface": "0",
    "Product_EstimatedRoofSizeFt": null,
    "Product_HomeSize": "Between2200And2800Ft",
    "Proposal_OptimalAmountOfPanels": 23,
    "Contact_LowMediumIncome": 0,
    "Contact_Utility": "Xcel",
    "Product_NumberOfStories": 2
  },
  {
    "RegistrationNumber": "SPUS46539",
    "CampaignName": "Minnesota 1 Summer 2024",
    "RegistrationStatus": "Declined",
    "Contact_Zip": "55430",
    "Contact_state": "MN",
    "Product_RoofPitch": "Inclined",
    "Product_RoofOrientation": "SouthWest",
    "Product_KnowsAmountOfPanels": "0",
    "Product_AmountOfPanels": null,
    "Product_CanEstimateRoofSurface": "0",
    "Product_EstimatedRoofSizeFt": null,
    "Product_HomeSize": "Between1000And1600Ft",
    "Proposal_OptimalAmountOfPanels": 15,
    "Contact_LowMediumIncome": 0,
    "Contact_Utility": "Xcel",
    "Product_NumberOfStories": 1
  },
  {
    "RegistrationNumber": "SPUS47397",
    "CampaignName": "Minnesota 1 Summer 2024",
    "RegistrationStatus": "Undecided",
    "Contact_Zip": "55419",
    "Contact_state": "MN",
    "Product_RoofPitch": "Sharp",
    "Product_RoofOrientation": "South",
    "Product_KnowsAmountOfPanels": "0",
    "Product_AmountOfPanels": null,
    "Product_CanEstimateRoofSurface": "0",
    "Product_EstimatedRoofSizeFt": null,
    "Product_HomeSize": "Between1600And2200Ft",
    "Proposal_OptimalAmountOfPanels": 19,
    "Contact_LowMediumIncome": 0,
    "Contact_Utility": "Xcel",
    "Product_NumberOfStories": 2
  },
  {
    "RegistrationNumber": "SPUS55004",
    "CampaignName": "Minnesota 1 Summer 2024",
    "RegistrationStatus": "Accepted",
    "Contact_Zip": "55406",
    "Contact_state": "MN",
    "Product_RoofPitch": "Inclined",
    "Product_RoofOrientation": "South",
    "Product_KnowsAmountOfPanels": "0",
    "Product_AmountOfPanels": null,
    "Product_CanEstimateRoofSurface": "1",
    "Product_EstimatedRoofSizeFt": 308,
    "Product_HomeSize": "Between1600And2200Ft",
    "Proposal_OptimalAmountOfPanels": 14,
    "Contact_LowMediumIncome": 0,
    "Contact_Utility": "Xcel",
    "Product_NumberOfStories": 1
  },
  {
    "RegistrationNumber": "SPUS45752",
    "CampaignName": "Minnesota 1 Summer 2024",
    "RegistrationStatus": "Undecided",
    "Contact_Zip": "55426",
    "Contact_state": "MN",
    "Product_RoofPitch": "Inclined",
    "Product_RoofOrientation": "South",
    "Product_KnowsAmountOfPanels": "0",
    "Product_AmountOfPanels": null,
    "Product_CanEstimateRoofSurface": "1",
    "Product_EstimatedRoofSizeFt": 800,
    "Product_HomeSize": null,
    "Proposal_OptimalAmountOfPanels": 8,
    "Contact_LowMediumIncome": 0,
    "Contact_Utility": "Xcel",
    "Product_NumberOfStories": 1
  },
  {
    "RegistrationNumber": "SPUS61452",
    "CampaignName": "Minnesota 1 Summer 2024",
    "RegistrationStatus": "Declined",
    "Contact_Zip": "55417",
    "Contact_state": "MN",
    "Product_RoofPitch": "Sharp",
    "Product_RoofOrientation": "SouthWest",
    "Product_KnowsAmountOfPanels": "0",
    "Product_AmountOfPanels": null,
    "Product_CanEstimateRoofSurface": "0",
    "Product_EstimatedRoofSizeFt": null,
    "Product_HomeSize": "Between1600And2200Ft",
    "Proposal_OptimalAmountOfPanels": 8,
    "Contact_LowMediumIncome": 0,
    "Contact_Utility": "Xcel",
    "Product_NumberOfStories": 1
  },
  {
    "RegistrationNumber": "SPUS53075",
    "CampaignName": "Minnesota 1 Summer 2024",
    "RegistrationStatus": "Undecided",
    "Contact_Zip": "55082",
    "Contact_state": "MN",
    "Product_RoofPitch": "Inclined",
    "Product_RoofOrientation": "East",
    "Product_KnowsAmountOfPanels": "0",
    "Product_AmountOfPanels": null,
    "Product_CanEstimateRoofSurface": "0",
    "Product_EstimatedRoofSizeFt": null,
    "Product_HomeSize": "LargerThan2800Ft",
    "Proposal_OptimalAmountOfPanels": 38,
    "Contact_LowMediumIncome": 0,
    "Contact_Utility": "Xcel",
    "Product_NumberOfStories": 2
  },
  {
    "RegistrationNumber": "SPUS55432",
    "CampaignName": "Minnesota 1 Summer 2024",
    "RegistrationStatus": "Accepted",
    "Contact_Zip": "55418",
    "Contact_state": "MN",
    "Product_RoofPitch": "Inclined",
    "Product_RoofOrientation": "SouthWest",
    "Product_KnowsAmountOfPanels": "1",
    "Product_AmountOfPanels": 27,
    "Product_CanEstimateRoofSurface": null,
    "Product_EstimatedRoofSizeFt": null,
    "Product_HomeSize": null,
    "Proposal_OptimalAmountOfPanels": 22,
    "Contact_LowMediumIncome": 0,
    "Contact_Utility": "Xcel",
    "Product_NumberOfStories": 2
  },
  {
    "RegistrationNumber": "SPUS42104",
    "CampaignName": "Minnesota 1 Summer 2024",
    "RegistrationStatus": "Undecided",
    "Contact_Zip": "55401",
    "Contact_state": "MN",
    "Product_RoofPitch": "Inclined",
    "Product_RoofOrientation": "South",
    "Product_KnowsAmountOfPanels": "0",
    "Product_AmountOfPanels": null,
    "Product_CanEstimateRoofSurface": "0",
    "Product_EstimatedRoofSizeFt": null,
    "Product_HomeSize": "Between2200And2800Ft",
    "Proposal_OptimalAmountOfPanels": 27,
    "Contact_LowMediumIncome": 1,
    "Contact_Utility": "Xcel",
    "Product_NumberOfStories": 2
  },
  {
    "RegistrationNumber": "SPUS55854",
    "CampaignName": "Minnesota 1 Summer 2024",
    "RegistrationStatus": "Undecided",
    "Contact_Zip": "55406",
    "Contact_state": "MN",
    "Product_RoofPitch": "Inclined",
    "Product_RoofOrientation": "South",
    "Product_KnowsAmountOfPanels": "1",
    "Product_AmountOfPanels": 9,
    "Product_CanEstimateRoofSurface": null,
    "Product_EstimatedRoofSizeFt": null,
    "Product_HomeSize": null,
    "Proposal_OptimalAmountOfPanels": 9,
    "Contact_LowMediumIncome": 0,
    "Contact_Utility": "Xcel",
    "Product_NumberOfStories": 2
  },
  {
    "RegistrationNumber": "SPUS63115",
    "CampaignName": "Minnesota 1 Summer 2024",
    "RegistrationStatus": "Undecided",
    "Contact_Zip": "55407",
    "Contact_state": "MN",
    "Product_RoofPitch": "Inclined",
    "Product_RoofOrientation": "SouthWest",
    "Product_KnowsAmountOfPanels": "0",
    "Product_AmountOfPanels": null,
    "Product_CanEstimateRoofSurface": "0",
    "Product_EstimatedRoofSizeFt": null,
    "Product_HomeSize": "SmallerThan1000Ft",
    "Proposal_OptimalAmountOfPanels": 13,
    "Contact_LowMediumIncome": 0,
    "Contact_Utility": "Xcel",
    "Product_NumberOfStories": 1
  },
  {
    "RegistrationNumber": "SPUS63748",
    "CampaignName": "Minnesota 1 Summer 2024",
    "RegistrationStatus": "Undecided",
    "Contact_Zip": "55418",
    "Contact_state": "MN",
    "Product_RoofPitch": "Inclined",
    "Product_RoofOrientation": "South",
    "Product_KnowsAmountOfPanels": "0",
    "Product_AmountOfPanels": null,
    "Product_CanEstimateRoofSurface": "0",
    "Product_EstimatedRoofSizeFt": null,
    "Product_HomeSize": "Between1600And2200Ft",
    "Proposal_OptimalAmountOfPanels": 23,
    "Contact_LowMediumIncome": 0,
    "Contact_Utility": "Xcel",
    "Product_NumberOfStories": 2
  },
  {
    "RegistrationNumber": "SPUS56065",
    "CampaignName": "Minnesota 1 Summer 2024",
    "RegistrationStatus": "Undecided",
    "Contact_Zip": "55443",
    "Contact_state": "MN",
    "Product_RoofPitch": "Inclined",
    "Product_RoofOrientation": "South",
    "Product_KnowsAmountOfPanels": "0",
    "Product_AmountOfPanels": null,
    "Product_CanEstimateRoofSurface": "1",
    "Product_EstimatedRoofSizeFt": 1000,
    "Product_HomeSize": "Between2200And2800Ft",
    "Proposal_OptimalAmountOfPanels": 21,
    "Contact_LowMediumIncome": 0,
    "Contact_Utility": "Xcel",
    "Product_NumberOfStories": 1
  },
  {
    "RegistrationNumber": "SPUS47174",
    "CampaignName": "Minnesota 1 Summer 2024",
    "RegistrationStatus": "Undecided",
    "Contact_Zip": "55419",
    "Contact_state": "MN",
    "Product_RoofPitch": "Inclined",
    "Product_RoofOrientation": "East",
    "Product_KnowsAmountOfPanels": "0",
    "Product_AmountOfPanels": null,
    "Product_CanEstimateRoofSurface": "0",
    "Product_EstimatedRoofSizeFt": null,
    "Product_HomeSize": "Between1000And1600Ft",
    "Proposal_OptimalAmountOfPanels": 20,
    "Contact_LowMediumIncome": 0,
    "Contact_Utility": "Xcel",
    "Product_NumberOfStories": 2
  }
]
