[
  {
    "Incentive name": "Federal Tax Credit",
    "Applicable community": "ALL",
    "Incentive source": "Federal Government",
    "LMI": "TRUE",
    "Incentive specs": "30% over the total cost of the installation",
    "Start date": "1 jan 2024",
    "End date": "No end date"
  },
  {
    "Incentive name": "Minneapolis Green Cost share",
    "Applicable community": "Minneapolis",
    "Incentive source": "State Government",
    "LMI": "TRUE",
    "Incentive specs": "40¢ per kiloWatt hour produced (Watt installed * roof efficiency implications * 0,40)",
    "Start date": "1 June 2024",
    "End date": "No end date"
  }
]
